AUTHORS
LICENCE
MANIFEST.in
README.md
requirements.txt
setup.cfg
setup.py
Tawhiri.egg-info/PKG-INFO
Tawhiri.egg-info/SOURCES.txt
Tawhiri.egg-info/dependency_links.txt
Tawhiri.egg-info/entry_points.txt
Tawhiri.egg-info/not-zip-safe
Tawhiri.egg-info/requires.txt
Tawhiri.egg-info/top_level.txt
deploy/gunicorn_cfg.py
deploy/logrotate.conf
deploy/nginx.conf
deploy/supervisord.conf
docs/.gitignore
docs/Makefile
docs/api.rst
docs/conf.py
docs/implementation.rst
docs/index.rst
docs/introduction.rst
docs/predictor.rst
docs/web_interface.rst
docs/wind_data.rst
docs/code/modules.rst
docs/code/tawhiri.rst
tawhiri/__init__.py
tawhiri/api.py
tawhiri/dataset.py
tawhiri/interpolate.c
tawhiri/interpolate.pyx
tawhiri/kml.py
tawhiri/manager.py
tawhiri/models.py
tawhiri/solver.c
tawhiri/solver.pyx
tawhiri/template.kml
ui/index.html
ui/css/base.css
ui/ext/css/bootstrap.min.css
ui/ext/css/jquery.datetimepicker.css
ui/ext/css/jquery.datetimepicker_license.txt
ui/ext/css/slider.css
ui/ext/fonts/glyphicons-halflings-regular.eot
ui/ext/fonts/glyphicons-halflings-regular.svg
ui/ext/fonts/glyphicons-halflings-regular.ttf
ui/ext/fonts/glyphicons-halflings-regular.woff
ui/ext/js/bootstrap-slider.js
ui/ext/js/bootstrap.min.js
ui/ext/js/html5shiv.js
ui/ext/js/jquery-1.10.2.min.js
ui/ext/js/jquery.datetimepicker.js
ui/ext/js/jquery.datetimepicker.js_license.txt
ui/ext/js/modernizr.custom.21490.js
ui/ext/js/respond.min.js
ui/js/cusf_tawhiri_ui.js
ui/js/predictions.js
ui/js/ui.js
ui/js/util.js