Metadata-Version: 1.1
Name: Tawhiri
Version: 0.2.0
Summary: High Altitude Balloon Landing Prediction Software
Home-page: http://www.cusf.co.uk/wiki/tawhiri:start
Author: Cambridge University Spaceflight
Author-email: contact@cusf.co.uk
License: GPLv3+
Platform: UNKNOWN
Classifier: Development Status :: 4 - Beta
Classifier: Intended Audience :: Science/Research
Classifier: License :: OSI Approved :: GNU General Public License v3 or later (GPLv3+)
Classifier: Programming Language :: Python :: 3.5
Classifier: Topic :: Scientific/Engineering
